{
 "updated": 1772936796.099391,
 "count": 233,
 "start_time": 1772936740.8944268,
 "mode": "LIVE",
 "governor": {
  "positions_open": 0,
  "positions_pending": 0,
  "positions_max": 3
 },
 "ws_stats": {
  "checks": 44885,
  "fires": 0
 },
 "game_scores": {
  "1356285": {
   "home": "Atlanta",
   "away": "Salt Lake",
   "home_score": 2,
   "away_score": 3,
   "state": "in",
   "period": 2,
   "clock": "83'",
   "detail": "83'"
  },
  "1356112": {
   "home": "Kings",
   "away": "Canadiens",
   "home_score": 3,
   "away_score": 2,
   "state": "in",
   "period": 3,
   "clock": "9:11",
   "detail": "9:11 - 3rd Period"
  },
  "1356107": {
   "home": "Maple Leafs",
   "away": "Lightning",
   "home_score": 1,
   "away_score": 4,
   "state": "in",
   "period": 3,
   "clock": "8:19",
   "detail": "8:19 - 3rd Period"
  },
  "1356097": {
   "home": "Blue Jackets",
   "away": "Mammoth",
   "home_score": 2,
   "away_score": 4,
   "state": "in",
   "period": 3,
   "clock": "9:03",
   "detail": "9:03 - 3rd Period"
  },
  "1356087": {
   "home": "Penguins",
   "away": "Flyers",
   "home_score": 3,
   "away_score": 4,
   "state": "post",
   "period": 5,
   "clock": "0:00",
   "detail": "Final/SO"
  },
  "1519624": {
   "home": "Grizzlies",
   "away": "Clippers",
   "home_score": 59,
   "away_score": 58,
   "state": "in",
   "period": 2,
   "clock": "0.0",
   "detail": "Halftime"
  },
  "1356102": {
   "home": "Jets",
   "away": "Canucks",
   "home_score": 1,
   "away_score": 2,
   "state": "in",
   "period": 3,
   "clock": "5:26",
   "detail": "5:26 - 3rd Period"
  },
  "1520387": {
   "home": "Bucks",
   "away": "Jazz",
   "home_score": 51,
   "away_score": 46,
   "state": "in",
   "period": 3,
   "clock": "11:01",
   "detail": "11:01 - 3rd Quarter"
  },
  "1356255": {
   "home": "Charlotte",
   "away": "Austin",
   "home_score": 2,
   "away_score": 1,
   "state": "in",
   "period": 2,
   "clock": "79'",
   "detail": "79'"
  }
 },
 "markets": [
  {
   "mid": "1479676",
   "title": "UC Davis Aggies vs. UC Irvine Anteaters",
   "typ": "match",
   "score": 145,
   "streak": 0,
   "yes_now": 0.59,
   "no_now": 0.43,
   "yes_low": 0.5,
   "no_low": 0.43,
   "yes_recent_low": 0.5,
   "no_recent_low": 0.43,
   "yes_high": 0.6,
   "no_high": 0.51,
   "combined_floor": 0.9299999999999999,
   "yes_depth": 81980.14,
   "no_depth": 105427.49,
   "age_secs": 35,
   "vol_yes": 0.1823,
   "vol_no": 0.1706,
   "vol24": 25933.763877999998,
   "momentum_side": null,
   "momentum_vel": 0,
   "momentum_score": 0,
   "falling_side": null,
   "lead_switches": 1,
   "triad_combined": null,
   "triad_slug": null,
   "triad_owned": 0,
   "trailing_state": "FIRST_BOUNCE",
   "trailing_first_side": "YES",
   "trailing_ready": false,
   "odds_edge": null,
   "odds_bonus": 0,
   "odds_movement": 0,
   "odds_elo_agrees": false
  },
  {
   "mid": "1518855",
   "title": "Warriors vs. Thunder: O/U 219.5",
   "typ": "ou",
   "score": 127,
   "streak": 0,
   "yes_now": 0.8,
   "no_now": 0.24,
   "yes_low": 0.74,
   "no_low": 0.24,
   "yes_recent_low": 0.74,
   "no_recent_low": 0.24,
   "yes_high": 0.83,
   "no_high": 0.43,
   "combined_floor": 0.98,
   "yes_depth": 34875.08,
   "no_depth": 102396.03,
   "age_secs": 35,
   "vol_yes": 0.1162,
   "vol_no": 0.6556,
   "vol24": 324207.124682,
   "momentum_side": null,
   "momentum_vel": 0,
   "momentum_score": 0,
   "falling_side": null,
   "lead_switches": 0,
   "triad_combined": null,
   "triad_slug": null,
   "triad_owned": 0,
   "trailing_state": "FIRST_BOUNCE",
   "trailing_first_side": "YES",
   "trailing_ready": false,
   "odds_edge": -0.6633,
   "odds_bonus": 40,
   "odds_movement": 0,
   "odds_elo_agrees": false
  },
  {
   "mid": "1520766",
   "title": "Spread: Texas Longhorns (-7.5)",
   "typ": "spread",
   "score": 122,
   "streak": 0,
   "yes_now": 0.53,
   "no_now": 0.53,
   "yes_low": 0.48,
   "no_low": 0.52,
   "yes_recent_low": 0.48,
   "no_recent_low": 0.52,
   "yes_high": 0.53,
   "no_high": 0.58,
   "combined_floor": 1.0,
   "yes_depth": 59067.09,
   "no_depth": 65259.28,
   "age_secs": 35,
   "vol_yes": 0.1013,
   "vol_no": 0.105,
   "vol24": 11926.111806,
   "momentum_side": "YES",
   "momentum_vel": 0.00135,
   "momentum_score": 15,
   "falling_side": null,
   "lead_switches": 1,
   "triad_combined": null,
   "triad_slug": null,
   "triad_owned": 0,
   "trailing_state": "FIRST_BOUNCE",
   "trailing_first_side": "YES",
   "trailing_ready": false,
   "odds_edge": null,
   "odds_bonus": 0,
   "odds_movement": 0,
   "odds_elo_agrees": false
  },
  {
   "mid": "1519625",
   "title": "Spread: Thunder (-15.5)",
   "typ": "spread",
   "score": 97,
   "streak": 0,
   "yes_now": 0.44,
   "no_now": 0.6,
   "yes_low": 0.43,
   "no_low": 0.57,
   "yes_recent_low": 0.43,
   "no_recent_low": 0.57,
   "yes_high": 0.48,
   "no_high": 0.88,
   "combined_floor": 1.0,
   "yes_depth": 6262.16,
   "no_depth": 6833.24,
   "age_secs": 35,
   "vol_yes": 0.1107,
   "vol_no": 0.4754,
   "vol24": 91525.29697400003,
   "momentum_side": null,
   "momentum_vel": 0,
   "momentum_score": 0,
   "falling_side": null,
   "lead_switches": 0,
   "triad_combined": null,
   "triad_slug": null,
   "triad_owned": 0,
   "trailing_state": "READY",
   "trailing_first_side": "YES",
   "trailing_ready": true,
   "odds_edge": null,
   "odds_bonus": 0,
   "odds_movement": 0,
   "odds_elo_agrees": false
  },
  {
   "mid": "1447482",
   "title": "First Round Pool A: Puerto Rico vs. Panama",
   "typ": "match",
   "score": 85,
   "streak": 0,
   "yes_now": 0.3,
   "no_now": 0.72,
   "yes_low": 0.27,
   "no_low": 0.71,
   "yes_recent_low": 0.27,
   "no_recent_low": 0.71,
   "yes_high": 0.32,
   "no_high": 0.78,
   "combined_floor": 0.98,
   "yes_depth": 44441.15,
   "no_depth": 4494.79,
   "age_secs": 35,
   "vol_yes": 0.17,
   "vol_no": 0.0952,
   "vol24": 65263.38023300004,
   "momentum_side": null,
   "momentum_vel": 0,
   "momentum_score": 0,
   "falling_side": null,
   "lead_switches": 0,
   "triad_combined": null,
   "triad_slug": null,
   "triad_owned": 0,
   "trailing_state": "FIRST_BOUNCE",
   "trailing_first_side": "YES",
   "trailing_ready": false,
   "odds_edge": null,
   "odds_bonus": 0,
   "odds_movement": 0,
   "odds_elo_agrees": false
  },
  {
   "mid": "1512645",
   "title": "BNP Paribas Open: Katerina Siniakova vs Leylah Fer",
   "typ": "match",
   "score": 85,
   "streak": 0,
   "yes_now": 0.38,
   "no_now": 0.63,
   "yes_low": 0.38,
   "no_low": 0.57,
   "yes_recent_low": 0.38,
   "no_recent_low": 0.57,
   "yes_high": 0.45,
   "no_high": 0.63,
   "combined_floor": 0.95,
   "yes_depth": 140998.55,
   "no_depth": 139510.44,
   "age_secs": 35,
   "vol_yes": 0.1653,
   "vol_no": 0.101,
   "vol24": 104982.49892600003,
   "momentum_side": null,
   "momentum_vel": 0,
   "momentum_score": 0,
   "falling_side": null,
   "lead_switches": 0,
   "triad_combined": null,
   "triad_slug": null,
   "triad_owned": 0,
   "trailing_state": "FIRST_BOUNCE",
   "trailing_first_side": "NO",
   "trailing_ready": false,
   "odds_edge": null,
   "odds_bonus": 0,
   "odds_movement": 0,
   "odds_elo_agrees": false
  },
  {
   "mid": "1479675",
   "title": "Oklahoma Sooners vs. Texas Longhorns",
   "typ": "match",
   "score": 77,
   "streak": 0,
   "yes_now": 0.22,
   "no_now": 0.8,
   "yes_low": 0.21,
   "no_low": 0.78,
   "yes_recent_low": 0.21,
   "no_recent_low": 0.78,
   "yes_high": 0.25,
   "no_high": 0.81,
   "combined_floor": 0.99,
   "yes_depth": 96398.69,
   "no_depth": 39193.48,
   "age_secs": 35,
   "vol_yes": 0.1697,
   "vol_no": 0.0382,
   "vol24": 42501.492345000006,
   "momentum_side": null,
   "momentum_vel": 0,
   "momentum_score": 0,
   "falling_side": null,
   "lead_switches": 0,
   "triad_combined": null,
   "triad_slug": null,
   "triad_owned": 0,
   "trailing_state": "FIRST_BOUNCE",
   "trailing_first_side": "NO",
   "trailing_ready": false,
   "odds_edge": null,
   "odds_bonus": 0,
   "odds_movement": 0,
   "odds_elo_agrees": false
  },
  {
   "mid": "1518254",
   "title": "Spread: Thunder (-14.5)",
   "typ": "spread",
   "score": 77,
   "streak": 0,
   "yes_now": 0.47,
   "no_now": 0.58,
   "yes_low": 0.47,
   "no_low": 0.54,
   "yes_recent_low": 0.47,
   "no_recent_low": 0.54,
   "yes_high": 0.5,
   "no_high": 0.59,
   "combined_floor": 1.01,
   "yes_depth": 70507.15,
   "no_depth": 77501.35,
   "age_secs": 35,
   "vol_yes": 0.062,
   "vol_no": 0.0882,
   "vol24": 256672.87782300005,
   "momentum_side": null,
   "momentum_vel": 0,
   "momentum_score": 0,
   "falling_side": null,
   "lead_switches": 0,
   "triad_combined": null,
   "triad_slug": null,
   "triad_owned": 0,
   "trailing_state": "FIRST_BOUNCE",
   "trailing_first_side": "NO",
   "trailing_ready": false,
   "odds_edge": null,
   "odds_bonus": 0,
   "odds_movement": 0,
   "odds_elo_agrees": false
  },
  {
   "mid": "1476097",
   "title": "Warriors vs. Thunder",
   "typ": "match",
   "score": 68,
   "streak": 0,
   "yes_now": 0.14,
   "no_now": 0.87,
   "yes_low": 0.12,
   "no_low": 0.87,
   "yes_recent_low": 0.12,
   "no_recent_low": 0.87,
   "yes_high": 0.14,
   "no_high": 0.9,
   "combined_floor": 0.99,
   "yes_depth": 129437.11,
   "no_depth": 139826.24,
   "age_secs": 35,
   "vol_yes": 0.1535,
   "vol_no": 0.034,
   "vol24": 2662973.6062849984,
   "momentum_side": null,
   "momentum_vel": 0,
   "momentum_score": 0,
   "falling_side": null,
   "lead_switches": 0,
   "triad_combined": null,
   "triad_slug": null,
   "triad_owned": 0,
   "trailing_state": "WATCHING",
   "trailing_first_side": null,
   "trailing_ready": false,
   "odds_edge": -0.0033,
   "odds_bonus": 0,
   "odds_movement": 0,
   "odds_elo_agrees": false
  },
  {
   "mid": "1483500",
   "title": "Celtics vs. Cavaliers",
   "typ": "match",
   "score": 68,
   "streak": 0,
   "yes_now": 0.5,
   "no_now": 0.51,
   "yes_low": 0.5,
   "no_low": 0.51,
   "yes_recent_low": 0.5,
   "no_recent_low": 0.51,
   "yes_high": 0.5,
   "no_high": 0.51,
   "combined_floor": 1.01,
   "yes_depth": 51740.97,
   "no_depth": 50012.26,
   "age_secs": 35,
   "vol_yes": 0.0,
   "vol_no": 0.0,
   "vol24": 123489.117222,
   "momentum_side": null,
   "momentum_vel": 0,
   "momentum_score": 0,
   "falling_side": null,
   "lead_switches": 0,
   "triad_combined": null,
   "triad_slug": null,
   "triad_owned": 0,
   "trailing_state": "WATCHING",
   "trailing_first_side": null,
   "trailing_ready": false,
   "odds_edge": -0.0084,
   "odds_bonus": 0,
   "odds_movement": 0,
   "odds_elo_agrees": true
  },
  {
   "mid": "1460839",
   "title": "UFC 326: Michael Johnson vs. Drew Dober (Lightweig",
   "typ": "match",
   "score": 65,
   "streak": 0,
   "yes_now": 0.46,
   "no_now": 0.55,
   "yes_low": 0.46,
   "no_low": 0.54,
   "yes_recent_low": 0.46,
   "no_recent_low": 0.54,
   "yes_high": 0.48,
   "no_high": 0.55,
   "combined_floor": 1.0,
   "yes_depth": 47905.312600000005,
   "no_depth": 141969.59780000002,
   "age_secs": 35,
   "vol_yes": 0.0428,
   "vol_no": 0.0183,
   "vol24": 1245826.943690999,
   "momentum_side": null,
   "momentum_vel": 0,
   "momentum_score": 0,
   "falling_side": null,
   "lead_switches": 0,
   "triad_combined": null,
   "triad_slug": null,
   "triad_owned": 0,
   "trailing_state": "WATCHING",
   "trailing_first_side": null,
   "trailing_ready": false,
   "odds_edge": null,
   "odds_bonus": 0,
   "odds_movement": 0,
   "odds_elo_agrees": false
  },
  {
   "mid": "1479673",
   "title": "Utah Valley Wolverines vs. Utah Tech Trailblazers",
   "typ": "match",
   "score": 60,
   "streak": 0,
   "yes_now": 0.63,
   "no_now": 0.4,
   "yes_low": 0.61,
   "no_low": 0.39,
   "yes_recent_low": 0.61,
   "no_recent_low": 0.39,
   "yes_high": 0.64,
   "no_high": 0.41,
   "combined_floor": 1.0,
   "yes_depth": 82768.29,
   "no_depth": 95009.06,
   "age_secs": 35,
   "vol_yes": 0.0487,
   "vol_no": 0.0502,
   "vol24": 10989.896854,
   "momentum_side": null,
   "momentum_vel": 0,
   "momentum_score": 0,
   "falling_side": null,
   "lead_switches": 0,
   "triad_combined": null,
   "triad_slug": null,
   "triad_owned": 0,
   "trailing_state": "FIRST_BOUNCE",
   "trailing_first_side": "YES",
   "trailing_ready": false,
   "odds_edge": null,
   "odds_bonus": 0,
   "odds_movement": 0,
   "odds_elo_agrees": false
  },
  {
   "mid": "1483515",
   "title": "Hornets vs. Suns",
   "typ": "match",
   "score": 60,
   "streak": 0,
   "yes_now": 0.63,
   "no_now": 0.38,
   "yes_low": 0.63,
   "no_low": 0.37,
   "yes_recent_low": 0.63,
   "no_recent_low": 0.37,
   "yes_high": 0.64,
   "no_high": 0.38,
   "combined_floor": 1.0,
   "yes_depth": 44407.49,
   "no_depth": 40323.63,
   "age_secs": 35,
   "vol_yes": 0.0158,
   "vol_no": 0.0266,
   "vol24": 19077.689205000002,
   "momentum_side": null,
   "momentum_vel": 0,
   "momentum_score": 0,
   "falling_side": null,
   "lead_switches": 0,
   "triad_combined": null,
   "triad_slug": null,
   "triad_owned": 0,
   "trailing_state": "WATCHING",
   "trailing_first_side": null,
   "trailing_ready": false,
   "odds_edge": -0.0158,
   "odds_bonus": 0,
   "odds_movement": 0,
   "odds_elo_agrees": false
  },
  {
   "mid": "1356122",
   "title": "Islanders vs. Sharks",
   "typ": "match",
   "score": 58,
   "streak": 0,
   "yes_now": 0.58,
   "no_now": 0.43,
   "yes_low": 0.58,
   "no_low": 0.43,
   "yes_recent_low": 0.58,
   "no_recent_low": 0.43,
   "yes_high": 0.58,
   "no_high": 0.43,
   "combined_floor": 1.01,
   "yes_depth": 342134.01,
   "no_depth": 351754.88,
   "age_secs": 35,
   "vol_yes": 0.0,
   "vol_no": 0.0,
   "vol24": 735759.9591599999,
   "momentum_side": null,
   "momentum_vel": 0,
   "momentum_score": 0,
   "falling_side": null,
   "lead_switches": 0,
   "triad_combined": null,
   "triad_slug": null,
   "triad_owned": 0,
   "trailing_state": "WATCHING",
   "trailing_first_side": null,
   "trailing_ready": false,
   "odds_edge": null,
   "odds_bonus": 0,
   "odds_movement": 0,
   "odds_elo_agrees": false
  },
  {
   "mid": "1447499",
   "title": "First Round Pool B: USA vs. Great Britain",
   "typ": "match",
   "score": 58,
   "streak": 0,
   "yes_now": 0.9,
   "no_now": 0.142,
   "yes_low": 0.882,
   "no_low": 0.127,
   "yes_recent_low": 0.882,
   "no_recent_low": 0.127,
   "yes_high": 0.913,
   "no_high": 0.154,
   "combined_floor": 1.009,
   "yes_depth": 102700.74,
   "no_depth": 157290.95,
   "age_secs": 35,
   "vol_yes": 0.0342,
   "vol_no": 0.1976,
   "vol24": 63850.57815499998,
   "momentum_side": null,
   "momentum_vel": 0,
   "momentum_score": 0,
   "falling_side": null,
   "lead_switches": 0,
   "triad_combined": null,
   "triad_slug": null,
   "triad_owned": 0,
   "trailing_state": "FIRST_BOUNCE",
   "trailing_first_side": "YES",
   "trailing_ready": false,
   "odds_edge": null,
   "odds_bonus": 0,
   "odds_movement": 0,
   "odds_elo_agrees": false
  },
  {
   "mid": "1356117",
   "title": "Senators vs. Kraken",
   "typ": "match",
   "score": 58,
   "streak": 0,
   "yes_now": 0.6090003000100003,
   "no_now": 0.4,
   "yes_low": 0.6090003000100003,
   "no_low": 0.4,
   "yes_recent_low": 0.6090003000100003,
   "no_recent_low": 0.4,
   "yes_high": 0.61,
   "no_high": 0.4,
   "combined_floor": 1.0090003000100003,
   "yes_depth": 646590.48,
   "no_depth": 304083.8,
   "age_secs": 35,
   "vol_yes": 0.0016,
   "vol_no": 0.0,
   "vol24": 239786.42755400005,
   "momentum_side": null,
   "momentum_vel": 0,
   "momentum_score": 0,
   "falling_side": null,
   "lead_switches": 0,
   "triad_combined": null,
   "triad_slug": null,
   "triad_owned": 0,
   "trailing_state": "WATCHING",
   "trailing_first_side": null,
   "trailing_ready": false,
   "odds_edge": null,
   "odds_bonus": 0,
   "odds_movement": 0,
   "odds_elo_agrees": false
  },
  {
   "mid": "1483502",
   "title": "Knicks vs. Lakers",
   "typ": "match",
   "score": 58,
   "streak": 0,
   "yes_now": 0.6,
   "no_now": 0.41,
   "yes_low": 0.6,
   "no_low": 0.41,
   "yes_recent_low": 0.6,
   "no_recent_low": 0.41,
   "yes_high": 0.6,
   "no_high": 0.41,
   "combined_floor": 1.01,
   "yes_depth": 74166.56,
   "no_depth": 43685.49,
   "age_secs": 35,
   "vol_yes": 0.0,
   "vol_no": 0.0,
   "vol24": 110546.98736999997,
   "momentum_side": null,
   "momentum_vel": 0,
   "momentum_score": 0,
   "falling_side": null,
   "lead_switches": 0,
   "triad_combined": null,
   "triad_slug": null,
   "triad_owned": 0,
   "trailing_state": "WATCHING",
   "trailing_first_side": null,
   "trailing_ready": false,
   "odds_edge": 0.0007,
   "odds_bonus": 0,
   "odds_movement": 0,
   "odds_elo_agrees": false
  },
  {
   "mid": "1356315",
   "title": "Will Vancouver Whitecaps FC win on 2026-03-07?",
   "typ": "win",
   "score": 58,
   "streak": 0,
   "yes_now": 0.5690010715561375,
   "no_now": 0.439000900090009,
   "yes_low": 0.5690010715561375,
   "no_low": 0.439000900090009,
   "yes_recent_low": 0.5690010715561375,
   "no_recent_low": 0.439000900090009,
   "yes_high": 0.57,
   "no_high": 0.44,
   "combined_floor": 1.0080019716461466,
   "yes_depth": 189588.93,
   "no_depth": 197928.83,
   "age_secs": 35,
   "vol_yes": 0.0018,
   "vol_no": 0.0023,
   "vol24": 243005.11803199982,
   "momentum_side": null,
   "momentum_vel": 0,
   "momentum_score": 0,
   "falling_side": null,
   "lead_switches": 0,
   "triad_combined": null,
   "triad_slug": null,
   "triad_owned": 0,
   "trailing_state": "WATCHING",
   "trailing_first_side": null,
   "trailing_ready": false,
   "odds_edge": null,
   "odds_bonus": 0,
   "odds_movement": 0,
   "odds_elo_agrees": false
  },
  {
   "mid": "1512636",
   "title": "BNP Paribas Open: Ugo Humbert vs Alex Michelsen",
   "typ": "match",
   "score": 57,
   "streak": 0,
   "yes_now": 0.47,
   "no_now": 0.54,
   "yes_low": 0.47,
   "no_low": 0.53,
   "yes_recent_low": 0.47,
   "no_recent_low": 0.53,
   "yes_high": 0.49,
   "no_high": 0.54,
   "combined_floor": 1.0,
   "yes_depth": 81516.21,
   "no_depth": 70347.18,
   "age_secs": 35,
   "vol_yes": 0.0421,
   "vol_no": 0.0186,
   "vol24": 48215.595792999986,
   "momentum_side": null,
   "momentum_vel": 0,
   "momentum_score": 0,
   "falling_side": null,
   "lead_switches": 0,
   "triad_combined": null,
   "triad_slug": null,
   "triad_owned": 0,
   "trailing_state": "WATCHING",
   "trailing_first_side": null,
   "trailing_ready": false,
   "odds_edge": null,
   "odds_bonus": 0,
   "odds_movement": 0,
   "odds_elo_agrees": false
  },
  {
   "mid": "1479685",
   "title": "Texas Tech Red Raiders vs. BYU Cougars",
   "typ": "match",
   "score": 55,
   "streak": 0,
   "yes_now": 0.399000900090009,
   "no_now": 0.61,
   "yes_low": 0.399000900090009,
   "no_low": 0.61,
   "yes_recent_low": 0.399000900090009,
   "no_recent_low": 0.61,
   "yes_high": 0.4,
   "no_high": 0.61,
   "combined_floor": 1.009000900090009,
   "yes_depth": 141881.53,
   "no_depth": 135329.32,
   "age_secs": 35,
   "vol_yes": 0.0025,
   "vol_no": 0.0,
   "vol24": 35929.915343,
   "momentum_side": null,
   "momentum_vel": 0,
   "momentum_score": 0,
   "falling_side": null,
   "lead_switches": 0,
   "triad_combined": null,
   "triad_slug": null,
   "triad_owned": 0,
   "trailing_state": "WATCHING",
   "trailing_first_side": null,
   "trailing_ready": false,
   "odds_edge": null,
   "odds_bonus": 0,
   "odds_movement": 0,
   "odds_elo_agrees": false
  },
  {
   "mid": "1356299",
   "title": "Will San Diego FC win on 2026-03-07?",
   "typ": "win",
   "score": 55,
   "streak": 0,
   "yes_now": 0.77,
   "no_now": 0.25,
   "yes_low": 0.77,
   "no_low": 0.24,
   "yes_recent_low": 0.77,
   "no_recent_low": 0.24,
   "yes_high": 0.78,
   "no_high": 0.25,
   "combined_floor": 1.01,
   "yes_depth": 14166.7,
   "no_depth": 59091.2,
   "age_secs": 35,
   "vol_yes": 0.013,
   "vol_no": 0.0407,
   "vol24": 663444.8011319996,
   "momentum_side": null,
   "momentum_vel": 0,
   "momentum_score": 0,
   "falling_side": null,
   "lead_switches": 0,
   "triad_combined": null,
   "triad_slug": null,
   "triad_owned": 0,
   "trailing_state": "WATCHING",
   "trailing_first_side": null,
   "trailing_ready": false,
   "odds_edge": null,
   "odds_bonus": 0,
   "odds_movement": 0,
   "odds_elo_agrees": false
  },
  {
   "mid": "1356307",
   "title": "Will Colorado Rapids SC win on 2026-03-07?",
   "typ": "win",
   "score": 55,
   "streak": 0,
   "yes_now": 0.46,
   "no_now": 0.55,
   "yes_low": 0.46,
   "no_low": 0.55,
   "yes_recent_low": 0.46,
   "no_recent_low": 0.55,
   "yes_high": 0.46,
   "no_high": 0.55,
   "combined_floor": 1.01,
   "yes_depth": 220629.06,
   "no_depth": 215205.91,
   "age_secs": 35,
   "vol_yes": 0.0,
   "vol_no": 0.0,
   "vol24": 28089.451011999998,
   "momentum_side": null,
   "momentum_vel": 0,
   "momentum_score": 0,
   "falling_side": null,
   "lead_switches": 0,
   "triad_combined": null,
   "triad_slug": null,
   "triad_owned": 0,
   "trailing_state": "WATCHING",
   "trailing_first_side": null,
   "trailing_ready": false,
   "odds_edge": null,
   "odds_bonus": 0,
   "odds_movement": 0,
   "odds_elo_agrees": false
  },
  {
   "mid": "1356386",
   "title": "Will Tigres de la UANL win on 2026-03-07?",
   "typ": "win",
   "score": 55,
   "streak": 0,
   "yes_now": 0.5090069284064666,
   "no_now": 0.4990025006946374,
   "yes_low": 0.5090069284064666,
   "no_low": 0.4990025006946374,
   "yes_recent_low": 0.5090069284064666,
   "no_recent_low": 0.4990025006946374,
   "yes_high": 0.51,
   "no_high": 0.5,
   "combined_floor": 1.008009429101104,
   "yes_depth": 72657.4,
   "no_depth": 77100.58,
   "age_secs": 35,
   "vol_yes": 0.002,
   "vol_no": 0.002,
   "vol24": 21336.744255,
   "momentum_side": null,
   "momentum_vel": 0,
   "momentum_score": 0,
   "falling_side": null,
   "lead_switches": 0,
   "triad_combined": null,
   "triad_slug": null,
   "triad_owned": 0,
   "trailing_state": "WATCHING",
   "trailing_first_side": null,
   "trailing_ready": false,
   "odds_edge": null,
   "odds_bonus": 0,
   "odds_movement": 0,
   "odds_elo_agrees": false
  },
  {
   "mid": "1390472",
   "title": "UFC 326: Gregory Rodrigues vs. Brunno Ferreira (Mi",
   "typ": "match",
   "score": 55,
   "streak": 0,
   "yes_now": 0.61,
   "no_now": 0.4,
   "yes_low": 0.61,
   "no_low": 0.4,
   "yes_recent_low": 0.61,
   "no_recent_low": 0.4,
   "yes_high": 0.61,
   "no_high": 0.4,
   "combined_floor": 1.01,
   "yes_depth": 144471.9717,
   "no_depth": 19640.966,
   "age_secs": 35,
   "vol_yes": 0.0,
   "vol_no": 0.0,
   "vol24": 732338.9129020002,
   "momentum_side": null,
   "momentum_vel": 0,
   "momentum_score": 0,
   "falling_side": null,
   "lead_switches": 0,
   "triad_combined": null,
   "triad_slug": null,
   "triad_owned": 0,
   "trailing_state": "WATCHING",
   "trailing_first_side": null,
   "trailing_ready": false,
   "odds_edge": null,
   "odds_bonus": 0,
   "odds_movement": 0,
   "odds_elo_agrees": false
  },
  {
   "mid": "1378736",
   "title": "UFC 326: Charles Oliveira vs. Max Holloway (Lightw",
   "typ": "match",
   "score": 55,
   "streak": 0,
   "yes_now": 0.36,
   "no_now": 0.65,
   "yes_low": 0.36,
   "no_low": 0.65,
   "yes_recent_low": 0.36,
   "no_recent_low": 0.65,
   "yes_high": 0.36,
   "no_high": 0.65,
   "combined_floor": 1.01,
   "yes_depth": 189687.88,
   "no_depth": 403624.65,
   "age_secs": 35,
   "vol_yes": 0.0,
   "vol_no": 0.0,
   "vol24": 1935434.3591950003,
   "momentum_side": null,
   "momentum_vel": 0,
   "momentum_score": 0,
   "falling_side": null,
   "lead_switches": 0,
   "triad_combined": null,
   "triad_slug": null,
   "triad_owned": 0,
   "trailing_state": "WATCHING",
   "trailing_first_side": null,
   "trailing_ready": false,
   "odds_edge": null,
   "odds_bonus": 0,
   "odds_movement": 0,
   "odds_elo_agrees": false
  },
  {
   "mid": "1378746",
   "title": "O/U 2.5 Rounds",
   "typ": "ou",
   "score": 54,
   "streak": 0,
   "yes_now": 0.55,
   "no_now": 0.46,
   "yes_low": 0.55,
   "no_low": 0.46,
   "yes_recent_low": 0.55,
   "no_recent_low": 0.46,
   "yes_high": 0.55,
   "no_high": 0.46,
   "combined_floor": 1.01,
   "yes_depth": 7475.56,
   "no_depth": 9880.55,
   "age_secs": 35,
   "vol_yes": 0.0,
   "vol_no": 0.0,
   "vol24": 16089.385602,
   "momentum_side": null,
   "momentum_vel": 0,
   "momentum_score": 0,
   "falling_side": null,
   "lead_switches": 0,
   "triad_combined": null,
   "triad_slug": null,
   "triad_owned": 0,
   "trailing_state": "WATCHING",
   "trailing_first_side": null,
   "trailing_ready": false,
   "odds_edge": null,
   "odds_bonus": 0,
   "odds_movement": 0,
   "odds_elo_agrees": false
  },
  {
   "mid": "1423626",
   "title": "Will Eintracht Frankfurt win on 2026-03-08?",
   "typ": "win",
   "score": 53,
   "streak": 0,
   "yes_now": 0.37,
   "no_now": 0.6390006618133686,
   "yes_low": 0.37,
   "no_low": 0.6390006618133686,
   "yes_recent_low": 0.37,
   "no_recent_low": 0.6390006618133686,
   "yes_high": 0.37,
   "no_high": 0.64,
   "combined_floor": 1.0090006618133684,
   "yes_depth": 191750.23,
   "no_depth": 389880.26,
   "age_secs": 35,
   "vol_yes": 0.0,
   "vol_no": 0.0016,
   "vol24": 100871.62241399998,
   "momentum_side": null,
   "momentum_vel": 0,
   "momentum_score": 0,
   "falling_side": null,
   "lead_switches": 0,
   "triad_combined": null,
   "triad_slug": null,
   "triad_owned": 0,
   "trailing_state": "WATCHING",
   "trailing_first_side": null,
   "trailing_ready": false,
   "odds_edge": null,
   "odds_bonus": 0,
   "odds_movement": 0,
   "odds_elo_agrees": false
  },
  {
   "mid": "1461194",
   "title": "Will Bologna FC 1909 win on 2026-03-08?",
   "typ": "win",
   "score": 53,
   "streak": 0,
   "yes_now": 0.6190005113926929,
   "no_now": 0.389001800360072,
   "yes_low": 0.6190005113926929,
   "no_low": 0.389001800360072,
   "yes_recent_low": 0.6190005113926929,
   "no_recent_low": 0.389001800360072,
   "yes_high": 0.62,
   "no_high": 0.39,
   "combined_floor": 1.0080023117527648,
   "yes_depth": 394198.19,
   "no_depth": 248684.38,
   "age_secs": 35,
   "vol_yes": 0.0016,
   "vol_no": 0.0026,
   "vol24": 119268.524573,
   "momentum_side": null,
   "momentum_vel": 0,
   "momentum_score": 0,
   "falling_side": null,
   "lead_switches": 0,
   "triad_combined": null,
   "triad_slug": null,
   "triad_owned": 0,
   "trailing_state": "WATCHING",
   "trailing_first_side": null,
   "trailing_ready": false,
   "odds_edge": null,
   "odds_bonus": 0,
   "odds_movement": 0,
   "odds_elo_agrees": false
  },
  {
   "mid": "1479688",
   "title": "Western Carolina Catamounts vs. Mercer Bears",
   "typ": "match",
   "score": 52,
   "streak": 0,
   "yes_now": 0.5,
   "no_now": 0.51,
   "yes_low": 0.5,
   "no_low": 0.51,
   "yes_recent_low": 0.5,
   "no_recent_low": 0.51,
   "yes_high": 0.5,
   "no_high": 0.51,
   "combined_floor": 1.01,
   "yes_depth": 99120.19,
   "no_depth": 92851.8,
   "age_secs": 35,
   "vol_yes": 0.0,
   "vol_no": 0.0,
   "vol24": 21242.149907,
   "momentum_side": null,
   "momentum_vel": 0,
   "momentum_score": 0,
   "falling_side": null,
   "lead_switches": 0,
   "triad_combined": null,
   "triad_slug": null,
   "triad_owned": 0,
   "trailing_state": "WATCHING",
   "trailing_first_side": null,
   "trailing_ready": false,
   "odds_edge": null,
   "odds_bonus": 0,
   "odds_movement": 0,
   "odds_elo_agrees": false
  },
  {
   "mid": "1510563",
   "title": "UFC 326: Gaston Bola\u00f1os vs. JeongYeong Lee (Feathe",
   "typ": "match",
   "score": 52,
   "streak": 0,
   "yes_now": 0.5,
   "no_now": 0.51,
   "yes_low": 0.5,
   "no_low": 0.5,
   "yes_recent_low": 0.5,
   "no_recent_low": 0.5,
   "yes_high": 0.5,
   "no_high": 0.51,
   "combined_floor": 1.0,
   "yes_depth": 22693.08,
   "no_depth": 17927.52,
   "age_secs": 35,
   "vol_yes": 0.0,
   "vol_no": 0.0197,
   "vol24": 38459.073562,
   "momentum_side": null,
   "momentum_vel": 0,
   "momentum_score": 0,
   "falling_side": null,
   "lead_switches": 0,
   "triad_combined": null,
   "triad_slug": null,
   "triad_owned": 0,
   "trailing_state": "WATCHING",
   "trailing_first_side": null,
   "trailing_ready": false,
   "odds_edge": null,
   "odds_bonus": 0,
   "odds_movement": 0,
   "odds_elo_agrees": false
  },
  {
   "mid": "1456055",
   "title": "Will FC Barcelona win on 2026-03-10?",
   "typ": "win",
   "score": 50,
   "streak": 0,
   "yes_now": 0.43,
   "no_now": 0.579001800360072,
   "yes_low": 0.43,
   "no_low": 0.579001800360072,
   "yes_recent_low": 0.43,
   "no_recent_low": 0.579001800360072,
   "yes_high": 0.43,
   "no_high": 0.58,
   "combined_floor": 1.009001800360072,
   "yes_depth": 48691.59,
   "no_depth": 76505.19,
   "age_secs": 35,
   "vol_yes": 0.0,
   "vol_no": 0.0017,
   "vol24": 147714.4427560001,
   "momentum_side": null,
   "momentum_vel": 0,
   "momentum_score": 0,
   "falling_side": null,
   "lead_switches": 0,
   "triad_combined": null,
   "triad_slug": null,
   "triad_owned": 0,
   "trailing_state": "WATCHING",
   "trailing_first_side": null,
   "trailing_ready": false,
   "odds_edge": null,
   "odds_bonus": 0,
   "odds_movement": 0,
   "odds_elo_agrees": false
  },
  {
   "mid": "1355976",
   "title": "Will Sparta Rotterdam win on 2026-03-08?",
   "typ": "win",
   "score": 50,
   "streak": 0,
   "yes_now": 0.5490037515631513,
   "no_now": 0.4590036014405762,
   "yes_low": 0.5490037515631513,
   "no_low": 0.4590036014405762,
   "yes_recent_low": 0.5490037515631513,
   "no_recent_low": 0.4590036014405762,
   "yes_high": 0.55,
   "no_high": 0.46,
   "combined_floor": 1.0080073530037275,
   "yes_depth": 249789.51,
   "no_depth": 184748.97,
   "age_secs": 35,
   "vol_yes": 0.0018,
   "vol_no": 0.0022,
   "vol24": 21144.694403999998,
   "momentum_side": null,
   "momentum_vel": 0,
   "momentum_score": 0,
   "falling_side": null,
   "lead_switches": 0,
   "triad_combined": null,
   "triad_slug": null,
   "triad_owned": 0,
   "trailing_state": "WATCHING",
   "trailing_first_side": null,
   "trailing_ready": false,
   "odds_edge": null,
   "odds_bonus": 0,
   "odds_movement": 0,
   "odds_elo_agrees": false
  },
  {
   "mid": "1417740",
   "title": "Will Villarreal CF win on 2026-03-08?",
   "typ": "win",
   "score": 50,
   "streak": 0,
   "yes_now": 0.66,
   "no_now": 0.35,
   "yes_low": 0.66,
   "no_low": 0.35,
   "yes_recent_low": 0.66,
   "no_recent_low": 0.35,
   "yes_high": 0.66,
   "no_high": 0.35,
   "combined_floor": 1.01,
   "yes_depth": 498902.42,
   "no_depth": 246050.85,
   "age_secs": 35,
   "vol_yes": 0.0,
   "vol_no": 0.0,
   "vol24": 42252.562569999995,
   "momentum_side": null,
   "momentum_vel": 0,
   "momentum_score": 0,
   "falling_side": null,
   "lead_switches": 0,
   "triad_combined": null,
   "triad_slug": null,
   "triad_owned": 0,
   "trailing_state": "WATCHING",
   "trailing_first_side": null,
   "trailing_ready": false,
   "odds_edge": null,
   "odds_bonus": 0,
   "odds_movement": 0,
   "odds_elo_agrees": false
  },
  {
   "mid": "1479677",
   "title": "California-San Diego Tritons vs. UC Santa Barbara ",
   "typ": "match",
   "score": 50,
   "streak": 0,
   "yes_now": 0.32,
   "no_now": 0.69,
   "yes_low": 0.32,
   "no_low": 0.69,
   "yes_recent_low": 0.32,
   "no_recent_low": 0.69,
   "yes_high": 0.34,
   "no_high": 0.7,
   "combined_floor": 1.01,
   "yes_depth": 89402.03,
   "no_depth": 28148.28,
   "age_secs": 35,
   "vol_yes": 0.0621,
   "vol_no": 0.0144,
   "vol24": 7998.352932,
   "momentum_side": null,
   "momentum_vel": 0,
   "momentum_score": 0,
   "falling_side": null,
   "lead_switches": 0,
   "triad_combined": null,
   "triad_slug": null,
   "triad_owned": 0,
   "trailing_state": "WATCHING",
   "trailing_first_side": null,
   "trailing_ready": false,
   "odds_edge": null,
   "odds_bonus": 0,
   "odds_movement": 0,
   "odds_elo_agrees": false
  },
  {
   "mid": "1417940",
   "title": "Spread: Villarreal CF (-1.5)",
   "typ": "spread",
   "score": 50,
   "streak": 0,
   "yes_now": 0.41,
   "no_now": 0.6,
   "yes_low": 0.41,
   "no_low": 0.6,
   "yes_recent_low": 0.41,
   "no_recent_low": 0.6,
   "yes_high": 0.41,
   "no_high": 0.6,
   "combined_floor": 1.01,
   "yes_depth": 193995.73,
   "no_depth": 212212.47,
   "age_secs": 35,
   "vol_yes": 0.0,
   "vol_no": 0.0,
   "vol24": 50760.95191800001,
   "momentum_side": null,
   "momentum_vel": 0,
   "momentum_score": 0,
   "falling_side": null,
   "lead_switches": 0,
   "triad_combined": null,
   "triad_slug": null,
   "triad_owned": 0,
   "trailing_state": "WATCHING",
   "trailing_first_side": null,
   "trailing_ready": false,
   "odds_edge": null,
   "odds_bonus": 0,
   "odds_movement": 0,
   "odds_elo_agrees": false
  },
  {
   "mid": "1483513",
   "title": "Rockets vs. Spurs",
   "typ": "match",
   "score": 50,
   "streak": 0,
   "yes_now": 0.35,
   "no_now": 0.66,
   "yes_low": 0.35,
   "no_low": 0.66,
   "yes_recent_low": 0.35,
   "no_recent_low": 0.66,
   "yes_high": 0.35,
   "no_high": 0.66,
   "combined_floor": 1.01,
   "yes_depth": 35683.26,
   "no_depth": 69818.79,
   "age_secs": 35,
   "vol_yes": 0.0,
   "vol_no": 0.0,
   "vol24": 29996.539011999994,
   "momentum_side": null,
   "momentum_vel": 0,
   "momentum_score": 0,
   "falling_side": null,
   "lead_switches": 0,
   "triad_combined": null,
   "triad_slug": null,
   "triad_owned": 0,
   "trailing_state": "WATCHING",
   "trailing_first_side": null,
   "trailing_ready": false,
   "odds_edge": -0.0016,
   "odds_bonus": 0,
   "odds_movement": 0,
   "odds_elo_agrees": false
  },
  {
   "mid": "1479683",
   "title": "Northwestern Wildcats vs. Minnesota Golden Gophers",
   "typ": "match",
   "score": 50,
   "streak": 0,
   "yes_now": 0.13,
   "no_now": 0.88,
   "yes_low": 0.12,
   "no_low": 0.88,
   "yes_recent_low": 0.12,
   "no_recent_low": 0.88,
   "yes_high": 0.14,
   "no_high": 0.89,
   "combined_floor": 1.0,
   "yes_depth": 86249.41,
   "no_depth": 37107.48,
   "age_secs": 35,
   "vol_yes": 0.1559,
   "vol_no": 0.0113,
   "vol24": 42905.22502400002,
   "momentum_side": null,
   "momentum_vel": 0,
   "momentum_score": 0,
   "falling_side": null,
   "lead_switches": 0,
   "triad_combined": null,
   "triad_slug": null,
   "triad_owned": 0,
   "trailing_state": "WATCHING",
   "trailing_first_side": null,
   "trailing_ready": false,
   "odds_edge": null,
   "odds_bonus": 0,
   "odds_movement": 0,
   "odds_elo_agrees": false
  },
  {
   "mid": "1483511",
   "title": "Magic vs. Bucks",
   "typ": "match",
   "score": 50,
   "streak": 0,
   "yes_now": 0.58,
   "no_now": 0.43,
   "yes_low": 0.58,
   "no_low": 0.43,
   "yes_recent_low": 0.58,
   "no_recent_low": 0.43,
   "yes_high": 0.58,
   "no_high": 0.43,
   "combined_floor": 1.01,
   "yes_depth": 25256.01,
   "no_depth": 32972.0,
   "age_secs": 35,
   "vol_yes": 0.0,
   "vol_no": 0.0,
   "vol24": 43683.861754,
   "momentum_side": null,
   "momentum_vel": 0,
   "momentum_score": 0,
   "falling_side": null,
   "lead_switches": 0,
   "triad_combined": null,
   "triad_slug": null,
   "triad_owned": 0,
   "trailing_state": "WATCHING",
   "trailing_first_side": null,
   "trailing_ready": false,
   "odds_edge": -0.0251,
   "odds_bonus": 0,
   "odds_movement": 0,
   "odds_elo_agrees": false
  },
  {
   "mid": "1360162",
   "title": "Blues vs. Ducks",
   "typ": "match",
   "score": 50,
   "streak": 0,
   "yes_now": 0.4,
   "no_now": 0.61,
   "yes_low": 0.4,
   "no_low": 0.61,
   "yes_recent_low": 0.4,
   "no_recent_low": 0.61,
   "yes_high": 0.4,
   "no_high": 0.61,
   "combined_floor": 1.01,
   "yes_depth": 24942.56,
   "no_depth": 48314.63,
   "age_secs": 35,
   "vol_yes": 0.0,
   "vol_no": 0.0,
   "vol24": 16199.813283,
   "momentum_side": null,
   "momentum_vel": 0,
   "momentum_score": 0,
   "falling_side": null,
   "lead_switches": 0,
   "triad_combined": null,
   "triad_slug": null,
   "triad_owned": 0,
   "trailing_state": "WATCHING",
   "trailing_first_side": null,
   "trailing_ready": false,
   "odds_edge": null,
   "odds_bonus": 0,
   "odds_movement": 0,
   "odds_elo_agrees": false
  },
  {
   "mid": "1513428",
   "title": "Set Handicap: Rinderknech (-1.5) vs Cerundolo (+1.",
   "typ": "spread",
   "score": 49,
   "streak": 0,
   "yes_now": 0.5,
   "no_now": 0.51,
   "yes_low": 0.5,
   "no_low": 0.51,
   "yes_recent_low": 0.5,
   "no_recent_low": 0.51,
   "yes_high": 0.5,
   "no_high": 0.51,
   "combined_floor": 1.01,
   "yes_depth": 238385.01,
   "no_depth": 239449.17,
   "age_secs": 35,
   "vol_yes": 0.0,
   "vol_no": 0.0,
   "vol24": 15380.028158000003,
   "momentum_side": null,
   "momentum_vel": 0,
   "momentum_score": 0,
   "falling_side": null,
   "lead_switches": 0,
   "triad_combined": null,
   "triad_slug": null,
   "triad_owned": 0,
   "trailing_state": "WATCHING",
   "trailing_first_side": null,
   "trailing_ready": false,
   "odds_edge": null,
   "odds_bonus": 0,
   "odds_movement": 0,
   "odds_elo_agrees": false
  },
  {
   "mid": "1513151",
   "title": "Cerundolo vs. Rinderknech: Set 1 Games O/U 8.5",
   "typ": "ou",
   "score": 49,
   "streak": 0,
   "yes_now": 0.51,
   "no_now": 0.5,
   "yes_low": 0.51,
   "no_low": 0.5,
   "yes_recent_low": 0.51,
   "no_recent_low": 0.5,
   "yes_high": 0.51,
   "no_high": 0.5,
   "combined_floor": 1.01,
   "yes_depth": 238558.67,
   "no_depth": 234642.05,
   "age_secs": 35,
   "vol_yes": 0.0,
   "vol_no": 0.0,
   "vol24": 22515.760128999988,
   "momentum_side": null,
   "momentum_vel": 0,
   "momentum_score": 0,
   "falling_side": null,
   "lead_switches": 0,
   "triad_combined": null,
   "triad_slug": null,
   "triad_owned": 0,
   "trailing_state": "WATCHING",
   "trailing_first_side": null,
   "trailing_ready": false,
   "odds_edge": null,
   "odds_bonus": 0,
   "odds_movement": 0,
   "odds_elo_agrees": false
  },
  {
   "mid": "1513153",
   "title": "Cerundolo vs. Rinderknech: Match O/U 23.5",
   "typ": "ou",
   "score": 49,
   "streak": 0,
   "yes_now": 0.5,
   "no_now": 0.51,
   "yes_low": 0.5,
   "no_low": 0.51,
   "yes_recent_low": 0.5,
   "no_recent_low": 0.51,
   "yes_high": 0.5,
   "no_high": 0.51,
   "combined_floor": 1.01,
   "yes_depth": 237734.94,
   "no_depth": 235732.28,
   "age_secs": 35,
   "vol_yes": 0.0,
   "vol_no": 0.0,
   "vol24": 18298.347831000003,
   "momentum_side": null,
   "momentum_vel": 0,
   "momentum_score": 0,
   "falling_side": null,
   "lead_switches": 0,
   "triad_combined": null,
   "triad_slug": null,
   "triad_owned": 0,
   "trailing_state": "WATCHING",
   "trailing_first_side": null,
   "trailing_ready": false,
   "odds_edge": null,
   "odds_bonus": 0,
   "odds_movement": 0,
   "odds_elo_agrees": false
  },
  {
   "mid": "1513155",
   "title": "Cerundolo vs. Rinderknech: Set 1 Games O/U 10.5",
   "typ": "ou",
   "score": 49,
   "streak": 0,
   "yes_now": 0.5,
   "no_now": 0.51,
   "yes_low": 0.5,
   "no_low": 0.51,
   "yes_recent_low": 0.5,
   "no_recent_low": 0.51,
   "yes_high": 0.5,
   "no_high": 0.51,
   "combined_floor": 1.01,
   "yes_depth": 240840.39,
   "no_depth": 248059.14,
   "age_secs": 35,
   "vol_yes": 0.0,
   "vol_no": 0.0,
   "vol24": 20692.422504999926,
   "momentum_side": null,
   "momentum_vel": 0,
   "momentum_score": 0,
   "falling_side": null,
   "lead_switches": 0,
   "triad_combined": null,
   "triad_slug": null,
   "triad_owned": 0,
   "trailing_state": "WATCHING",
   "trailing_first_side": null,
   "trailing_ready": false,
   "odds_edge": null,
   "odds_bonus": 0,
   "odds_movement": 0,
   "odds_elo_agrees": false
  },
  {
   "mid": "1483509",
   "title": "Wizards vs. Pelicans",
   "typ": "match",
   "score": 48,
   "streak": 0,
   "yes_now": 0.23,
   "no_now": 0.78,
   "yes_low": 0.23,
   "no_low": 0.78,
   "yes_recent_low": 0.23,
   "no_recent_low": 0.78,
   "yes_high": 0.23,
   "no_high": 0.78,
   "combined_floor": 1.01,
   "yes_depth": 52126.06,
   "no_depth": 324645.59,
   "age_secs": 35,
   "vol_yes": 0.0,
   "vol_no": 0.0,
   "vol24": 238349.28958200003,
   "momentum_side": null,
   "momentum_vel": 0,
   "momentum_score": 0,
   "falling_side": null,
   "lead_switches": 0,
   "triad_combined": null,
   "triad_slug": null,
   "triad_owned": 0,
   "trailing_state": "WATCHING",
   "trailing_first_side": null,
   "trailing_ready": false,
   "odds_edge": 0.0167,
   "odds_bonus": 0,
   "odds_movement": 0,
   "odds_elo_agrees": false
  },
  {
   "mid": "1461204",
   "title": "Will AC Milan vs. FC Internazionale Milano end in ",
   "typ": "draw",
   "score": 48,
   "streak": 0,
   "yes_now": 0.31,
   "no_now": 0.699001800360072,
   "yes_low": 0.31,
   "no_low": 0.699001800360072,
   "yes_recent_low": 0.31,
   "no_recent_low": 0.699001800360072,
   "yes_high": 0.31,
   "no_high": 0.7,
   "combined_floor": 1.009001800360072,
   "yes_depth": 163518.46,
   "no_depth": 393886.53,
   "age_secs": 35,
   "vol_yes": 0.0,
   "vol_no": 0.0014,
   "vol24": 19693.597447,
   "momentum_side": null,
   "momentum_vel": 0,
   "momentum_score": 0,
   "falling_side": null,
   "lead_switches": 0,
   "triad_combined": null,
   "triad_slug": null,
   "triad_owned": 0,
   "trailing_state": "WATCHING",
   "trailing_first_side": null,
   "trailing_ready": false,
   "odds_edge": null,
   "odds_bonus": 0,
   "odds_movement": 0,
   "odds_elo_agrees": false
  },
  {
   "mid": "1423614",
   "title": "Will FC St. Pauli 1910 win on 2026-03-08?",
   "typ": "win",
   "score": 48,
   "streak": 0,
   "yes_now": 0.35,
   "no_now": 0.659001800360072,
   "yes_low": 0.3490009375976664,
   "no_low": 0.659001800360072,
   "yes_recent_low": 0.3490009375976664,
   "no_recent_low": 0.659001800360072,
   "yes_high": 0.35,
   "no_high": 0.66,
   "combined_floor": 1.0080027379577385,
   "yes_depth": 185411.91,
   "no_depth": 429421.83,
   "age_secs": 35,
   "vol_yes": 0.0029,
   "vol_no": 0.0015,
   "vol24": 81563.96461199998,
   "momentum_side": null,
   "momentum_vel": 0,
   "momentum_score": 0,
   "falling_side": null,
   "lead_switches": 0,
   "triad_combined": null,
   "triad_slug": null,
   "triad_owned": 0,
   "trailing_state": "WATCHING",
   "trailing_first_side": null,
   "trailing_ready": false,
   "odds_edge": null,
   "odds_bonus": 0,
   "odds_movement": 0,
   "odds_elo_agrees": false
  },
  {
   "mid": "1483517",
   "title": "Pacers vs. Trail Blazers",
   "typ": "match",
   "score": 48,
   "streak": 0,
   "yes_now": 0.23,
   "no_now": 0.78,
   "yes_low": 0.23,
   "no_low": 0.78,
   "yes_recent_low": 0.23,
   "no_recent_low": 0.78,
   "yes_high": 0.23,
   "no_high": 0.78,
   "combined_floor": 1.01,
   "yes_depth": 34417.44,
   "no_depth": 284736.16,
   "age_secs": 35,
   "vol_yes": 0.0,
   "vol_no": 0.0,
   "vol24": 111220.06701899997,
   "momentum_side": null,
   "momentum_vel": 0,
   "momentum_score": 0,
   "falling_side": null,
   "lead_switches": 0,
   "triad_combined": null,
   "triad_slug": null,
   "triad_owned": 0,
   "trailing_state": "WATCHING",
   "trailing_first_side": null,
   "trailing_ready": false,
   "odds_edge": 0.0221,
   "odds_bonus": 0,
   "odds_movement": 0,
   "odds_elo_agrees": false
  },
  {
   "mid": "1424415",
   "title": "Sparta Rotterdam vs. PEC Zwolle: O/U 2.5",
   "typ": "ou",
   "score": 47,
   "streak": 0,
   "yes_now": 0.64,
   "no_now": 0.37,
   "yes_low": 0.64,
   "no_low": 0.37,
   "yes_recent_low": 0.64,
   "no_recent_low": 0.37,
   "yes_high": 0.64,
   "no_high": 0.37,
   "combined_floor": 1.01,
   "yes_depth": 194634.39,
   "no_depth": 109166.85,
   "age_secs": 35,
   "vol_yes": 0.0,
   "vol_no": 0.0,
   "vol24": 19069.634752,
   "momentum_side": null,
   "momentum_vel": 0,
   "momentum_score": 0,
   "falling_side": null,
   "lead_switches": 0,
   "triad_combined": null,
   "triad_slug": null,
   "triad_owned": 0,
   "trailing_state": "WATCHING",
   "trailing_first_side": null,
   "trailing_ready": false,
   "odds_edge": null,
   "odds_bonus": 0,
   "odds_movement": 0,
   "odds_elo_agrees": false
  },
  {
   "mid": "1456052",
   "title": "Will FC Bayern M\u00fcnchen win on 2026-03-10?",
   "typ": "win",
   "score": 47,
   "streak": 0,
   "yes_now": 0.61,
   "no_now": 0.3990019153011279,
   "yes_low": 0.61,
   "no_low": 0.3990019153011279,
   "yes_recent_low": 0.61,
   "no_recent_low": 0.3990019153011279,
   "yes_high": 0.61,
   "no_high": 0.4,
   "combined_floor": 1.0090019153011278,
   "yes_depth": 680404.18,
   "no_depth": 134680.99,
   "age_secs": 35,
   "vol_yes": 0.0,
   "vol_no": 0.0025,
   "vol24": 26007.788363000007,
   "momentum_side": null,
   "momentum_vel": 0,
   "momentum_score": 0,
   "falling_side": null,
   "lead_switches": 0,
   "triad_combined": null,
   "triad_slug": null,
   "triad_owned": 0,
   "trailing_state": "WATCHING",
   "trailing_first_side": null,
   "trailing_ready": false,
   "odds_edge": null,
   "odds_bonus": 0,
   "odds_movement": 0,
   "odds_elo_agrees": false
  },
  {
   "mid": "1472836",
   "title": "Will Chelsea FC win on 2026-03-14?",
   "typ": "win",
   "score": 47,
   "streak": 0,
   "yes_now": 0.5490036014405762,
   "no_now": 0.46,
   "yes_low": 0.5490036014405762,
   "no_low": 0.46,
   "yes_recent_low": 0.5490036014405762,
   "no_recent_low": 0.46,
   "yes_high": 0.55,
   "no_high": 0.46,
   "combined_floor": 1.0090036014405763,
   "yes_depth": 186921.29,
   "no_depth": 144688.77,
   "age_secs": 35,
   "vol_yes": 0.0018,
   "vol_no": 0.0,
   "vol24": 30258.418349000003,
   "momentum_side": null,
   "momentum_vel": 0,
   "momentum_score": 0,
   "falling_side": null,
   "lead_switches": 0,
   "triad_combined": null,
   "triad_slug": null,
   "triad_owned": 0,
   "trailing_state": "WATCHING",
   "trailing_first_side": null,
   "trailing_ready": false,
   "odds_edge": null,
   "odds_bonus": 0,
   "odds_movement": 0,
   "odds_elo_agrees": false
  }
 ]
}